sheet0/__init__.py
sheet0-0.0.1.dist-info/METADATA
sheet0-0.0.1.dist-info/WHEEL
sheet0-0.0.1.dist-info/licenses/LICENSE
sheet0-0.0.1.dist-info/RECORD
