Metadata-Version: 2.4
Name: sheet0
Version: 0.0.1
Summary: Sheet0 - A powerful spreadsheet framework (coming soon)
Project-URL: Homepage, https://github.com/sheet0/sheet0
Project-URL: Documentation, https://github.com/sheet0/sheet0
Project-URL: Repository, https://github.com/sheet0/sheet0
Author: Sheet0 Team
License-Expression: Apache-2.0
License-File: LICENSE
Keywords: data,framework,sheet0,spreadsheet
Classifier: Development Status :: 1 - Planning
Classifier: Intended Audience :: Developers
Classifier: License :: OSI Approved :: Apache Software License
Classifier: Programming Language :: Python :: 3
Classifier: Programming Language :: Python :: 3.8
Classifier: Programming Language :: Python :: 3.9
Classifier: Programming Language :: Python :: 3.10
Classifier: Programming Language :: Python :: 3.11
Classifier: Programming Language :: Python :: 3.12
Requires-Python: >=3.8
